queue_fetcher/__init__.py
queue_fetcher/test.py
queue_fetcher/management/__init__.py
queue_fetcher/management/commands/__init__.py
queue_fetcher/management/commands/run_queue.py
queue_fetcher/tasks/__init__.py
queue_fetcher/tasks/base.py
queue_fetcher/utils/__init__.py
queue_fetcher/utils/mock_sqs.py
queue_fetcher/utils/sqs.py
queue_fetcher-2.0.5.dist-info/DESCRIPTION.rst
queue_fetcher-2.0.5.dist-info/METADATA
queue_fetcher-2.0.5.dist-info/RECORD
queue_fetcher-2.0.5.dist-info/WHEEL
queue_fetcher-2.0.5.dist-info/metadata.json
queue_fetcher-2.0.5.dist-info/top_level.txt
